jemplater/__init__.py
jemplater/__main__.py
jemplater/main.py
jemplater-1.0.3.dist-info/LICENSE
jemplater-1.0.3.dist-info/METADATA
jemplater-1.0.3.dist-info/WHEEL
jemplater-1.0.3.dist-info/entry_points.txt
jemplater-1.0.3.dist-info/top_level.txt
jemplater-1.0.3.dist-info/RECORD
