Metadata-Version: 2.1
Name: jemplater
Version: 1.0.3
Summary: A utility package for compiling template files using Jinja2 and JSON/YAML variable files
Author-email: Joe Garlick <joe@garlickbread.com>
Project-URL: Homepage, https://github.com/jcbjoe/jemplater
Project-URL: Issues, https://github.com/jcbjoe/jemplater/issues
Classifier: Intended Audience :: Information Technology
Classifier: Intended Audience :: System Administrators
Classifier: Operating System :: OS Independent
Classifier: Programming Language :: Python :: 3
Classifier: Programming Language :: Python
Classifier: Typing :: Typed
Classifier: Intended Audience :: Developers
Classifier: Programming Language :: Python :: 3 :: Only
Classifier: Programming Language :: Python :: 3.8
Classifier: Programming Language :: Python :: 3.9
Classifier: Programming Language :: Python :: 3.10
Classifier: Programming Language :: Python :: 3.11
Classifier: Programming Language :: Python :: 3.12
Classifier: License :: OSI Approved :: MIT License
Requires-Python: >=3.8
License-File: LICENSE
Requires-Dist: typer>=0.15.1
Requires-Dist: Jinja2>=3.0.0
Requires-Dist: PyYAML>=5.1.1
